reportspy/__init__.py
reportspy/core.cp312-win_amd64.pyd
reportspy-0.3.dist-info/METADATA
reportspy-0.3.dist-info/WHEEL
reportspy-0.3.dist-info/top_level.txt
reportspy-0.3.dist-info/RECORD
